django_serverless_oauth_session/__init__.py
django_serverless_oauth_session/apps.py
django_serverless_oauth_session/models.py
django_serverless_oauth_session/oauth.py
django_serverless_oauth_session/urls.py
django_serverless_oauth_session/utils.py
django_serverless_oauth_session/views.py
django_serverless_oauth_session-0.5.0.dist-info/LICENSE
django_serverless_oauth_session-0.5.0.dist-info/WHEEL
django_serverless_oauth_session-0.5.0.dist-info/METADATA
django_serverless_oauth_session-0.5.0.dist-info/RECORD
