Metadata-Version: 2.1
Name: django-serverless-oauth-session
Version: 0.5.0
Summary: Provides a Django app for storing tokens in AWS's DynamoDB, and providing a convenient requests session which uses the token. This is a use-case-specific library, and is intended for backend integrations that must authenticate with an API which only supports OAuth2 for its authentication protocol.
Home-page: https://github.com/brno32/django-serverless-oauth-session
License: MIT
Keywords: django,serverless,oauth,aws,dynamodb,requests,sessions
Author: Alex Drozd
Author-email: drozdster@gmail.com
Requires-Python: >=3.8,<4.0
Classifier: License :: OSI Approved :: MIT License
Classifier: Programming Language :: Python :: 3
Classifier: Programming Language :: Python :: 3.8
Classifier: Programming Language :: Python :: 3.9
Requires-Dist: Authlib (>=0.15.3,<0.16.0)
Requires-Dist: pynamodb (>=5.0.3,<6.0.0)
Project-URL: Repository, https://github.com/brno32/django-serverless-oauth-session
